psd/__init__.py
psd/algorithms.py
psd/config.py
psd/feature_flags.py
psd/framework_optimizers.py
psd/functions.py
psd/graph.py
psd/optimizer_tf.py
psd/py.typed
psd_optimizer/__init__.py
psd_optimizer/optimizer.py
psd_optimizer/perturbed_adam.py
psd_optimizer/py.typed
psd_optimizer-0.1.1.dist-info/licenses/LICENSE
psd_optimizer-0.1.1.dist-info/METADATA
psd_optimizer-0.1.1.dist-info/WHEEL
psd_optimizer-0.1.1.dist-info/top_level.txt
psd_optimizer-0.1.1.dist-info/RECORD
