Metadata-Version: 2.4
Name: psd-optimizer
Version: 0.1.1
Summary: Perturbed Saddle-point Descent optimizer for PyTorch
Author: PSD Authors
License: MIT
Project-URL: Homepage, https://github.com/farukalpay/PSD
Requires-Python: >=3.8
License-File: LICENSE
Requires-Dist: torch
Requires-Dist: torchvision
Requires-Dist: optuna
Requires-Dist: matplotlib
Provides-Extra: dev
Requires-Dist: pre-commit==3.5.0; extra == "dev"
Requires-Dist: mypy==1.10.0; extra == "dev"
Requires-Dist: ruff==0.1.7; extra == "dev"
Requires-Dist: pytest==7.4.4; extra == "dev"
Provides-Extra: docs
Requires-Dist: sphinx==7.2.6; extra == "docs"
Provides-Extra: bench
Requires-Dist: pytest-benchmark==4.0.0; extra == "bench"
Dynamic: license-file
